{
    "project_id":  "douyin_account_ops",
    "name":  "抖音代运营采集工具",
    "type":  "data_analysis",
    "status":  "active",
    "purpose":  "账号采集模块：输入抖音主页链接，输出标准 douyin_analysis_package.zip；当前阶段不扩展账号诊断、运营方案、脚本生成、自动发布或商家建档。新增输出命名、ZIP目录、防冲突和连续编号规则用于规范采集包与后续交付文件命名。",
    "current_stage":  "account_ops 账号采集模块多账号样本验证阶段",
    "current_task":  "继续用 5-10 条样本包采更多账号，观察评论、OCR、partial 类型；30 条正式包仅作阶段性验收。",
    "progress":  "当前 output/packages 与 output_zip 命名规则已通过多账号样本包验证；5 条/10 条样本包已多账号通过。",
    "default_collection_mode":  "public",
    "default_test_mode":  false,
    "default_max_works":  30,
    "output_naming_rule":  "{店铺名称}-{作品数量}-{时间}",
    "output_time_format":  "YYYYMMDD_HHMM",
    "zip_output_dir":  "/output_zip/",
    "zip_naming_rule":  "{店铺名称}-{作品数量三位数}-{时间}.zip",
    "blockers":  [
                     "继续观察评论、OCR、partial 类型。",
                     "30 条正式包只作为阶段性验收。",
                     "data_analysis 和 content_pipeline 暂不启动。"
                 ],
    "last_update":  "2026-06-28"
}